[
  {
    "id": "ACWI",
    "name": "iShares MSCI ACWI ETF",
    "ticker_stooq": null,
    "ticker_yfinance": "ACWI",
    "source": "yfinance",
    "asset_type": "benchmark",
    "country": null,
    "sector": null,
    "hierarchy_level": 1,
    "benchmark_id": null,
    "currency": "USD",
    "liquidity_tier": 1
  },
  {
    "id": "SPX",
    "name": "S&P 500",
    "ticker_stooq": "^SPX",
    "ticker_yfinance": null,
    "source": "stooq",
    "asset_type": "country_index",
    "country": "US",
    "sector": null,
    "hierarchy_level": 1,
    "benchmark_id": "ACWI",
    "currency": "USD",
    "liquidity_tier": 1
  },
  {
    "id": "NDQ",
    "name": "NASDAQ 100",
    "ticker_stooq": "^NDQ",
    "ticker_yfinance": null,
    "source": "stooq",
    "asset_type": "country_index",
    "country": "US",
    "sector": null,
    "hierarchy_level": 1,
    "benchmark_id": "ACWI",
    "currency": "USD",
    "liquidity_tier": 1
  },
  {
    "id": "FTM",
    "name": "FTSE 100",
    "ticker_stooq": "^FTM",
    "ticker_yfinance": null,
    "source": "stooq",
    "asset_type": "country_index",
    "country": "UK",
    "sector": null,
    "hierarchy_level": 1,
    "benchmark_id": "ACWI",
    "currency": "GBP",
    "liquidity_tier": 1
  },
  {
    "id": "DAX",
    "name": "DAX 40",
    "ticker_stooq": "^DAX",
    "ticker_yfinance": null,
    "source": "stooq",
    "asset_type": "country_index",
    "country": "DE",
    "sector": null,
    "hierarchy_level": 1,
    "benchmark_id": "ACWI",
    "currency": "EUR",
    "liquidity_tier": 1
  },
  {
    "id": "CAC",
    "name": "CAC 40",
    "ticker_stooq": "^CAC",
    "ticker_yfinance": null,
    "source": "stooq",
    "asset_type": "country_index",
    "country": "FR",
    "sector": null,
    "hierarchy_level": 1,
    "benchmark_id": "ACWI",
    "currency": "EUR",
    "liquidity_tier": 1
  },
  {
    "id": "NKX",
    "name": "Nikkei 225",
    "ticker_stooq": "^NKX",
    "ticker_yfinance": null,
    "source": "stooq",
    "asset_type": "country_index",
    "country": "JP",
    "sector": null,
    "hierarchy_level": 1,
    "benchmark_id": "ACWI",
    "currency": "JPY",
    "liquidity_tier": 1
  },
  {
    "id": "HSI",
    "name": "Hang Seng Index",
    "ticker_stooq": "^HSI",
    "ticker_yfinance": null,
    "source": "stooq",
    "asset_type": "country_index",
    "country": "HK",
    "sector": null,
    "hierarchy_level": 1,
    "benchmark_id": "ACWI",
    "currency": "HKD",
    "liquidity_tier": 1
  },
  {
    "id": "CSI300",
    "name": "CSI 300",
    "ticker_stooq": null,
    "ticker_yfinance": "000300.SS",
    "source": "yfinance",
    "asset_type": "country_index",
    "country": "CN",
    "sector": null,
    "hierarchy_level": 1,
    "benchmark_id": "ACWI",
    "currency": "CNY",
    "liquidity_tier": 1
  },
  {
    "id": "KS11",
    "name": "KOSPI",
    "ticker_stooq": null,
    "ticker_yfinance": "^KS11",
    "source": "yfinance",
    "asset_type": "country_index",
    "country": "KR",
    "sector": null,
    "hierarchy_level": 1,
    "benchmark_id": "ACWI",
    "currency": "KRW",
    "liquidity_tier": 1
  },
  {
    "id": "NSEI",
    "name": "NIFTY 50",
    "ticker_stooq": null,
    "ticker_yfinance": "^NSEI",
    "source": "yfinance",
    "asset_type": "country_index",
    "country": "IN",
    "sector": null,
    "hierarchy_level": 1,
    "benchmark_id": "ACWI",
    "currency": "INR",
    "liquidity_tier": 1
  },
  {
    "id": "TWII",
    "name": "TWSE",
    "ticker_stooq": null,
    "ticker_yfinance": "^TWII",
    "source": "yfinance",
    "asset_type": "country_index",
    "country": "TW",
    "sector": null,
    "hierarchy_level": 1,
    "benchmark_id": "ACWI",
    "currency": "TWD",
    "liquidity_tier": 1
  },
  {
    "id": "AXJO",
    "name": "ASX 200",
    "ticker_stooq": null,
    "ticker_yfinance": "^AXJO",
    "source": "yfinance",
    "asset_type": "country_index",
    "country": "AU",
    "sector": null,
    "hierarchy_level": 1,
    "benchmark_id": "ACWI",
    "currency": "AUD",
    "liquidity_tier": 1
  },
  {
    "id": "BVSP",
    "name": "IBOVESPA",
    "ticker_stooq": null,
    "ticker_yfinance": "^BVSP",
    "source": "yfinance",
    "asset_type": "country_index",
    "country": "BR",
    "sector": null,
    "hierarchy_level": 1,
    "benchmark_id": "ACWI",
    "currency": "BRL",
    "liquidity_tier": 1
  },
  {
    "id": "GSPTSE",
    "name": "TSX Composite",
    "ticker_stooq": null,
    "ticker_yfinance": "^GSPTSE",
    "source": "yfinance",
    "asset_type": "country_index",
    "country": "CA",
    "sector": null,
    "hierarchy_level": 1,
    "benchmark_id": "ACWI",
    "currency": "CAD",
    "liquidity_tier": 1
  },
  {
    "id": "SPY_US",
    "name": "SPDR S&P 500 ETF Trust",
    "ticker_stooq": "SPY.US",
    "ticker_yfinance": null,
    "source": "stooq",
    "asset_type": "country_etf",
    "country": "US",
    "sector": null,
    "hierarchy_level": 1,
    "benchmark_id": "SPX",
    "currency": "USD",
    "liquidity_tier": 1
  },
  {
    "id": "QQQ_US",
    "name": "Invesco QQQ Trust",
    "ticker_stooq": "QQQ.US",
    "ticker_yfinance": null,
    "source": "stooq",
    "asset_type": "country_etf",
    "country": "US",
    "sector": null,
    "hierarchy_level": 1,
    "benchmark_id": "NDQ",
    "currency": "USD",
    "liquidity_tier": 1
  },
  {
    "id": "EWU_US",
    "name": "iShares MSCI United Kingdom ETF",
    "ticker_stooq": "EWU.US",
    "ticker_yfinance": null,
    "source": "stooq",
    "asset_type": "country_etf",
    "country": "UK",
    "sector": null,
    "hierarchy_level": 1,
    "benchmark_id": "FTM",
    "currency": "USD",
    "liquidity_tier": 1
  },
  {
    "id": "EWG_US",
    "name": "iShares MSCI Germany ETF",
    "ticker_stooq": "EWG.US",
    "ticker_yfinance": null,
    "source": "stooq",
    "asset_type": "country_etf",
    "country": "DE",
    "sector": null,
    "hierarchy_level": 1,
    "benchmark_id": "DAX",
    "currency": "USD",
    "liquidity_tier": 1
  },
  {
    "id": "EWQ_US",
    "name": "iShares MSCI France ETF",
    "ticker_stooq": "EWQ.US",
    "ticker_yfinance": null,
    "source": "stooq",
    "asset_type": "country_etf",
    "country": "FR",
    "sector": null,
    "hierarchy_level": 1,
    "benchmark_id": "CAC",
    "currency": "USD",
    "liquidity_tier": 1
  },
  {
    "id": "EWJ_US",
    "name": "iShares MSCI Japan ETF",
    "ticker_stooq": "EWJ.US",
    "ticker_yfinance": null,
    "source": "stooq",
    "asset_type": "country_etf",
    "country": "JP",
    "sector": null,
    "hierarchy_level": 1,
    "benchmark_id": "NKX",
    "currency": "USD",
    "liquidity_tier": 1
  },
  {
    "id": "EWH_US",
    "name": "iShares MSCI Hong Kong ETF",
    "ticker_stooq": "EWH.US",
    "ticker_yfinance": null,
    "source": "stooq",
    "asset_type": "country_etf",
    "country": "HK",
    "sector": null,
    "hierarchy_level": 1,
    "benchmark_id": "HSI",
    "currency": "USD",
    "liquidity_tier": 1
  },
  {
    "id": "FXI_US",
    "name": "iShares China Large-Cap ETF",
    "ticker_stooq": "FXI.US",
    "ticker_yfinance": null,
    "source": "stooq",
    "asset_type": "country_etf",
    "country": "CN",
    "sector": null,
    "hierarchy_level": 1,
    "benchmark_id": "CSI300",
    "currency": "USD",
    "liquidity_tier": 1
  },
  {
    "id": "EWY_US",
    "name": "iShares MSCI South Korea ETF",
    "ticker_stooq": "EWY.US",
    "ticker_yfinance": null,
    "source": "stooq",
    "asset_type": "country_etf",
    "country": "KR",
    "sector": null,
    "hierarchy_level": 1,
    "benchmark_id": "KS11",
    "currency": "USD",
    "liquidity_tier": 1
  },
  {
    "id": "INDA_US",
    "name": "iShares MSCI India ETF",
    "ticker_stooq": "INDA.US",
    "ticker_yfinance": null,
    "source": "stooq",
    "asset_type": "country_etf",
    "country": "IN",
    "sector": null,
    "hierarchy_level": 1,
    "benchmark_id": "NSEI",
    "currency": "USD",
    "liquidity_tier": 1
  },
  {
    "id": "EWT_US",
    "name": "iShares MSCI Taiwan ETF",
    "ticker_stooq": "EWT.US",
    "ticker_yfinance": null,
    "source": "stooq",
    "asset_type": "country_etf",
    "country": "TW",
    "sector": null,
    "hierarchy_level": 1,
    "benchmark_id": "TWII",
    "currency": "USD",
    "liquidity_tier": 1
  },
  {
    "id": "EWA_US",
    "name": "iShares MSCI Australia ETF",
    "ticker_stooq": "EWA.US",
    "ticker_yfinance": null,
    "source": "stooq",
    "asset_type": "country_etf",
    "country": "AU",
    "sector": null,
    "hierarchy_level": 1,
    "benchmark_id": "AXJO",
    "currency": "USD",
    "liquidity_tier": 1
  },
  {
    "id": "EWZ_US",
    "name": "iShares MSCI Brazil ETF",
    "ticker_stooq": "EWZ.US",
    "ticker_yfinance": null,
    "source": "stooq",
    "asset_type": "country_etf",
    "country": "BR",
    "sector": null,
    "hierarchy_level": 1,
    "benchmark_id": "BVSP",
    "currency": "USD",
    "liquidity_tier": 1
  },
  {
    "id": "EWC_US",
    "name": "iShares MSCI Canada ETF",
    "ticker_stooq": "EWC.US",
    "ticker_yfinance": null,
    "source": "stooq",
    "asset_type": "country_etf",
    "country": "CA",
    "sector": null,
    "hierarchy_level": 1,
    "benchmark_id": "GSPTSE",
    "currency": "USD",
    "liquidity_tier": 1
  },
  {
    "id": "XLK_US",
    "name": "Technology Select Sector SPDR",
    "ticker_stooq": "XLK.US",
    "ticker_yfinance": null,
    "source": "stooq",
    "asset_type": "sector_etf",
    "country": "US",
    "sector": "technology",
    "hierarchy_level": 2,
    "benchmark_id": "SPX",
    "currency": "USD",
    "liquidity_tier": 1
  },
  {
    "id": "XLF_US",
    "name": "Financial Select Sector SPDR",
    "ticker_stooq": "XLF.US",
    "ticker_yfinance": null,
    "source": "stooq",
    "asset_type": "sector_etf",
    "country": "US",
    "sector": "financials",
    "hierarchy_level": 2,
    "benchmark_id": "SPX",
    "currency": "USD",
    "liquidity_tier": 1
  },
  {
    "id": "XLV_US",
    "name": "Health Care Select Sector SPDR",
    "ticker_stooq": "XLV.US",
    "ticker_yfinance": null,
    "source": "stooq",
    "asset_type": "sector_etf",
    "country": "US",
    "sector": "healthcare",
    "hierarchy_level": 2,
    "benchmark_id": "SPX",
    "currency": "USD",
    "liquidity_tier": 1
  },
  {
    "id": "XLY_US",
    "name": "Consumer Discretionary Select Sector SPDR",
    "ticker_stooq": "XLY.US",
    "ticker_yfinance": null,
    "source": "stooq",
    "asset_type": "sector_etf",
    "country": "US",
    "sector": "consumer_discretionary",
    "hierarchy_level": 2,
    "benchmark_id": "SPX",
    "currency": "USD",
    "liquidity_tier": 1
  },
  {
    "id": "XLP_US",
    "name": "Consumer Staples Select Sector SPDR",
    "ticker_stooq": "XLP.US",
    "ticker_yfinance": null,
    "source": "stooq",
    "asset_type": "sector_etf",
    "country": "US",
    "sector": "consumer_staples",
    "hierarchy_level": 2,
    "benchmark_id": "SPX",
    "currency": "USD",
    "liquidity_tier": 1
  },
  {
    "id": "XLE_US",
    "name": "Energy Select Sector SPDR",
    "ticker_stooq": "XLE.US",
    "ticker_yfinance": null,
    "source": "stooq",
    "asset_type": "sector_etf",
    "country": "US",
    "sector": "energy",
    "hierarchy_level": 2,
    "benchmark_id": "SPX",
    "currency": "USD",
    "liquidity_tier": 1
  },
  {
    "id": "XLI_US",
    "name": "Industrial Select Sector SPDR",
    "ticker_stooq": "XLI.US",
    "ticker_yfinance": null,
    "source": "stooq",
    "asset_type": "sector_etf",
    "country": "US",
    "sector": "industrials",
    "hierarchy_level": 2,
    "benchmark_id": "SPX",
    "currency": "USD",
    "liquidity_tier": 1
  },
  {
    "id": "XLB_US",
    "name": "Materials Select Sector SPDR",
    "ticker_stooq": "XLB.US",
    "ticker_yfinance": null,
    "source": "stooq",
    "asset_type": "sector_etf",
    "country": "US",
    "sector": "materials",
    "hierarchy_level": 2,
    "benchmark_id": "SPX",
    "currency": "USD",
    "liquidity_tier": 1
  },
  {
    "id": "XLRE_US",
    "name": "Real Estate Select Sector SPDR",
    "ticker_stooq": "XLRE.US",
    "ticker_yfinance": null,
    "source": "stooq",
    "asset_type": "sector_etf",
    "country": "US",
    "sector": "real_estate",
    "hierarchy_level": 2,
    "benchmark_id": "SPX",
    "currency": "USD",
    "liquidity_tier": 1
  },
  {
    "id": "XLU_US",
    "name": "Utilities Select Sector SPDR",
    "ticker_stooq": "XLU.US",
    "ticker_yfinance": null,
    "source": "stooq",
    "asset_type": "sector_etf",
    "country": "US",
    "sector": "utilities",
    "hierarchy_level": 2,
    "benchmark_id": "SPX",
    "currency": "USD",
    "liquidity_tier": 1
  },
  {
    "id": "XLC_US",
    "name": "Communication Services Select Sector SPDR",
    "ticker_stooq": "XLC.US",
    "ticker_yfinance": null,
    "source": "stooq",
    "asset_type": "sector_etf",
    "country": "US",
    "sector": "communication_services",
    "hierarchy_level": 2,
    "benchmark_id": "SPX",
    "currency": "USD",
    "liquidity_tier": 1
  },
  {
    "id": "CNXIT_IN",
    "name": "NIFTY IT",
    "ticker_stooq": null,
    "ticker_yfinance": "^CNXIT",
    "source": "yfinance",
    "asset_type": "sector_index",
    "country": "IN",
    "sector": "it",
    "hierarchy_level": 2,
    "benchmark_id": "NSEI",
    "currency": "INR",
    "liquidity_tier": 1
  },
  {
    "id": "NSEBANK_IN",
    "name": "NIFTY Bank",
    "ticker_stooq": null,
    "ticker_yfinance": "^NSEBANK",
    "source": "yfinance",
    "asset_type": "sector_index",
    "country": "IN",
    "sector": "bank",
    "hierarchy_level": 2,
    "benchmark_id": "NSEI",
    "currency": "INR",
    "liquidity_tier": 1
  },
  {
    "id": "CNXFIN_IN",
    "name": "NIFTY Financial Services",
    "ticker_stooq": null,
    "ticker_yfinance": "^CNXFIN",
    "source": "yfinance",
    "asset_type": "sector_index",
    "country": "IN",
    "sector": "financial_services",
    "hierarchy_level": 2,
    "benchmark_id": "NSEI",
    "currency": "INR",
    "liquidity_tier": 1
  },
  {
    "id": "CNXPHARMA_IN",
    "name": "NIFTY Pharma",
    "ticker_stooq": null,
    "ticker_yfinance": "^CNXPHARMA",
    "source": "yfinance",
    "asset_type": "sector_index",
    "country": "IN",
    "sector": "pharma",
    "hierarchy_level": 2,
    "benchmark_id": "NSEI",
    "currency": "INR",
    "liquidity_tier": 1
  },
  {
    "id": "CNXAUTO_IN",
    "name": "NIFTY Auto",
    "ticker_stooq": null,
    "ticker_yfinance": "^CNXAUTO",
    "source": "yfinance",
    "asset_type": "sector_index",
    "country": "IN",
    "sector": "auto",
    "hierarchy_level": 2,
    "benchmark_id": "NSEI",
    "currency": "INR",
    "liquidity_tier": 1
  },
  {
    "id": "CNXFMCG_IN",
    "name": "NIFTY FMCG",
    "ticker_stooq": null,
    "ticker_yfinance": "^CNXFMCG",
    "source": "yfinance",
    "asset_type": "sector_index",
    "country": "IN",
    "sector": "fmcg",
    "hierarchy_level": 2,
    "benchmark_id": "NSEI",
    "currency": "INR",
    "liquidity_tier": 1
  },
  {
    "id": "CNXMETAL_IN",
    "name": "NIFTY Metal",
    "ticker_stooq": null,
    "ticker_yfinance": "^CNXMETAL",
    "source": "yfinance",
    "asset_type": "sector_index",
    "country": "IN",
    "sector": "metal",
    "hierarchy_level": 2,
    "benchmark_id": "NSEI",
    "currency": "INR",
    "liquidity_tier": 1
  },
  {
    "id": "CNXREALTY_IN",
    "name": "NIFTY Realty",
    "ticker_stooq": null,
    "ticker_yfinance": "^CNXREALTY",
    "source": "yfinance",
    "asset_type": "sector_index",
    "country": "IN",
    "sector": "realty",
    "hierarchy_level": 2,
    "benchmark_id": "NSEI",
    "currency": "INR",
    "liquidity_tier": 1
  },
  {
    "id": "CNXENERGY_IN",
    "name": "NIFTY Energy",
    "ticker_stooq": null,
    "ticker_yfinance": "^CNXENERGY",
    "source": "yfinance",
    "asset_type": "sector_index",
    "country": "IN",
    "sector": "energy",
    "hierarchy_level": 2,
    "benchmark_id": "NSEI",
    "currency": "INR",
    "liquidity_tier": 1
  },
  {
    "id": "CNXINFRA_IN",
    "name": "NIFTY Infrastructure",
    "ticker_stooq": null,
    "ticker_yfinance": "^CNXINFRA",
    "source": "yfinance",
    "asset_type": "sector_index",
    "country": "IN",
    "sector": "infrastructure",
    "hierarchy_level": 2,
    "benchmark_id": "NSEI",
    "currency": "INR",
    "liquidity_tier": 1
  },
  {
    "id": "CNXPSUBANK_IN",
    "name": "NIFTY PSU Bank",
    "ticker_stooq": null,
    "ticker_yfinance": "^CNXPSUBANK",
    "source": "yfinance",
    "asset_type": "sector_index",
    "country": "IN",
    "sector": "psu_bank",
    "hierarchy_level": 2,
    "benchmark_id": "NSEI",
    "currency": "INR",
    "liquidity_tier": 1
  },
  {
    "id": "1615_JP",
    "name": "TOPIX Banks ETF",
    "ticker_stooq": "1615.JP",
    "ticker_yfinance": null,
    "source": "stooq",
    "asset_type": "sector_etf",
    "country": "JP",
    "sector": "banks",
    "hierarchy_level": 2,
    "benchmark_id": "NKX",
    "currency": "JPY",
    "liquidity_tier": 2
  },
  {
    "id": "1613_JP",
    "name": "TOPIX Electrical Equipment ETF",
    "ticker_stooq": "1613.JP",
    "ticker_yfinance": null,
    "source": "stooq",
    "asset_type": "sector_etf",
    "country": "JP",
    "sector": "electrical_equipment",
    "hierarchy_level": 2,
    "benchmark_id": "NKX",
    "currency": "JPY",
    "liquidity_tier": 2
  },
  {
    "id": "1617_JP",
    "name": "TOPIX Foods ETF",
    "ticker_stooq": "1617.JP",
    "ticker_yfinance": null,
    "source": "stooq",
    "asset_type": "sector_etf",
    "country": "JP",
    "sector": "foods",
    "hierarchy_level": 2,
    "benchmark_id": "NKX",
    "currency": "JPY",
    "liquidity_tier": 2
  },
  {
    "id": "1619_JP",
    "name": "TOPIX Construction ETF",
    "ticker_stooq": "1619.JP",
    "ticker_yfinance": null,
    "source": "stooq",
    "asset_type": "sector_etf",
    "country": "JP",
    "sector": "construction",
    "hierarchy_level": 2,
    "benchmark_id": "NKX",
    "currency": "JPY",
    "liquidity_tier": 2
  },
  {
    "id": "1621_JP",
    "name": "TOPIX Pharma ETF",
    "ticker_stooq": "1621.JP",
    "ticker_yfinance": null,
    "source": "stooq",
    "asset_type": "sector_etf",
    "country": "JP",
    "sector": "pharma",
    "hierarchy_level": 2,
    "benchmark_id": "NKX",
    "currency": "JPY",
    "liquidity_tier": 2
  },
  {
    "id": "1622_JP",
    "name": "TOPIX Transport Equipment ETF",
    "ticker_stooq": "1622.JP",
    "ticker_yfinance": null,
    "source": "stooq",
    "asset_type": "sector_etf",
    "country": "JP",
    "sector": "transport_equipment",
    "hierarchy_level": 2,
    "benchmark_id": "NKX",
    "currency": "JPY",
    "liquidity_tier": 2
  },
  {
    "id": "1623_JP",
    "name": "TOPIX Iron/Steel ETF",
    "ticker_stooq": "1623.JP",
    "ticker_yfinance": null,
    "source": "stooq",
    "asset_type": "sector_etf",
    "country": "JP",
    "sector": "iron_steel",
    "hierarchy_level": 2,
    "benchmark_id": "NKX",
    "currency": "JPY",
    "liquidity_tier": 2
  },
  {
    "id": "1633_JP",
    "name": "TOPIX Real Estate ETF",
    "ticker_stooq": "1633.JP",
    "ticker_yfinance": null,
    "source": "stooq",
    "asset_type": "sector_etf",
    "country": "JP",
    "sector": "real_estate",
    "hierarchy_level": 2,
    "benchmark_id": "NKX",
    "currency": "JPY",
    "liquidity_tier": 2
  },
  {
    "id": "HSTECH_HK",
    "name": "Hang Seng Tech Index",
    "ticker_stooq": null,
    "ticker_yfinance": "^HSTECH",
    "source": "yfinance",
    "asset_type": "sector_index",
    "country": "HK",
    "sector": "technology",
    "hierarchy_level": 2,
    "benchmark_id": "HSI",
    "currency": "HKD",
    "liquidity_tier": 1
  },
  {
    "id": "HSFI_HK",
    "name": "Hang Seng Finance Index",
    "ticker_stooq": null,
    "ticker_yfinance": "^HSFI",
    "source": "yfinance",
    "asset_type": "sector_index",
    "country": "HK",
    "sector": "finance",
    "hierarchy_level": 2,
    "benchmark_id": "HSI",
    "currency": "HKD",
    "liquidity_tier": 1
  },
  {
    "id": "HSPI_HK",
    "name": "Hang Seng Properties Index",
    "ticker_stooq": null,
    "ticker_yfinance": "^HSPI",
    "source": "yfinance",
    "asset_type": "sector_index",
    "country": "HK",
    "sector": "properties",
    "hierarchy_level": 2,
    "benchmark_id": "HSI",
    "currency": "HKD",
    "liquidity_tier": 1
  },
  {
    "id": "HSUI_HK",
    "name": "Hang Seng Utilities Index",
    "ticker_stooq": null,
    "ticker_yfinance": "^HSUI",
    "source": "yfinance",
    "asset_type": "sector_index",
    "country": "HK",
    "sector": "utilities",
    "hierarchy_level": 2,
    "benchmark_id": "HSI",
    "currency": "HKD",
    "liquidity_tier": 1
  },
  {
    "id": "IXN_US",
    "name": "iShares Global Tech ETF",
    "ticker_stooq": "IXN.US",
    "ticker_yfinance": null,
    "source": "stooq",
    "asset_type": "global_sector_etf",
    "country": null,
    "sector": "technology",
    "hierarchy_level": 2,
    "benchmark_id": "ACWI",
    "currency": "USD",
    "liquidity_tier": 1
  },
  {
    "id": "IXG_US",
    "name": "iShares Global Financials ETF",
    "ticker_stooq": "IXG.US",
    "ticker_yfinance": null,
    "source": "stooq",
    "asset_type": "global_sector_etf",
    "country": null,
    "sector": "financials",
    "hierarchy_level": 2,
    "benchmark_id": "ACWI",
    "currency": "USD",
    "liquidity_tier": 1
  },
  {
    "id": "IXJ_US",
    "name": "iShares Global Healthcare ETF",
    "ticker_stooq": "IXJ.US",
    "ticker_yfinance": null,
    "source": "stooq",
    "asset_type": "global_sector_etf",
    "country": null,
    "sector": "healthcare",
    "hierarchy_level": 2,
    "benchmark_id": "ACWI",
    "currency": "USD",
    "liquidity_tier": 1
  },
  {
    "id": "IXC_US",
    "name": "iShares Global Energy ETF",
    "ticker_stooq": "IXC.US",
    "ticker_yfinance": null,
    "source": "stooq",
    "asset_type": "global_sector_etf",
    "country": null,
    "sector": "energy",
    "hierarchy_level": 2,
    "benchmark_id": "ACWI",
    "currency": "USD",
    "liquidity_tier": 1
  },
  {
    "id": "EXI_US",
    "name": "iShares Global Industrials ETF",
    "ticker_stooq": "EXI.US",
    "ticker_yfinance": null,
    "source": "stooq",
    "asset_type": "global_sector_etf",
    "country": null,
    "sector": "industrials",
    "hierarchy_level": 2,
    "benchmark_id": "ACWI",
    "currency": "USD",
    "liquidity_tier": 1
  },
  {
    "id": "RXI_US",
    "name": "iShares Global Consumer Discretionary ETF",
    "ticker_stooq": "RXI.US",
    "ticker_yfinance": null,
    "source": "stooq",
    "asset_type": "global_sector_etf",
    "country": null,
    "sector": "consumer_discretionary",
    "hierarchy_level": 2,
    "benchmark_id": "ACWI",
    "currency": "USD",
    "liquidity_tier": 1
  },
  {
    "id": "KXI_US",
    "name": "iShares Global Consumer Staples ETF",
    "ticker_stooq": "KXI.US",
    "ticker_yfinance": null,
    "source": "stooq",
    "asset_type": "global_sector_etf",
    "country": null,
    "sector": "consumer_staples",
    "hierarchy_level": 2,
    "benchmark_id": "ACWI",
    "currency": "USD",
    "liquidity_tier": 1
  },
  {
    "id": "JXI_US",
    "name": "iShares Global Utilities ETF",
    "ticker_stooq": "JXI.US",
    "ticker_yfinance": null,
    "source": "stooq",
    "asset_type": "global_sector_etf",
    "country": null,
    "sector": "utilities",
    "hierarchy_level": 2,
    "benchmark_id": "ACWI",
    "currency": "USD",
    "liquidity_tier": 1
  },
  {
    "id": "MXI_US",
    "name": "iShares Global Materials ETF",
    "ticker_stooq": "MXI.US",
    "ticker_yfinance": null,
    "source": "stooq",
    "asset_type": "global_sector_etf",
    "country": null,
    "sector": "materials",
    "hierarchy_level": 2,
    "benchmark_id": "ACWI",
    "currency": "USD",
    "liquidity_tier": 1
  },
  {
    "id": "IXP_US",
    "name": "iShares Global Comm Services ETF",
    "ticker_stooq": "IXP.US",
    "ticker_yfinance": null,
    "source": "stooq",
    "asset_type": "global_sector_etf",
    "country": null,
    "sector": "communication_services",
    "hierarchy_level": 2,
    "benchmark_id": "ACWI",
    "currency": "USD",
    "liquidity_tier": 1
  },
  {
    "id": "GLD_US",
    "name": "SPDR Gold Shares",
    "ticker_stooq": "GLD.US",
    "ticker_yfinance": null,
    "source": "stooq",
    "asset_type": "benchmark",
    "country": null,
    "sector": null,
    "hierarchy_level": 1,
    "benchmark_id": null,
    "currency": "USD",
    "liquidity_tier": 1
  },
  {
    "id": "SHY_US",
    "name": "iShares 1-3 Year Treasury Bond ETF",
    "ticker_stooq": "SHY.US",
    "ticker_yfinance": null,
    "source": "stooq",
    "asset_type": "benchmark",
    "country": null,
    "sector": null,
    "hierarchy_level": 1,
    "benchmark_id": null,
    "currency": "USD",
    "liquidity_tier": 1
  },
  {
    "id": "EEM_US",
    "name": "iShares MSCI Emerging Markets ETF",
    "ticker_stooq": "EEM.US",
    "ticker_yfinance": null,
    "source": "stooq",
    "asset_type": "benchmark",
    "country": null,
    "sector": null,
    "hierarchy_level": 1,
    "benchmark_id": null,
    "currency": "USD",
    "liquidity_tier": 1
  },
  {
    "id": "VEA_US",
    "name": "Vanguard FTSE Developed Markets ETF",
    "ticker_stooq": "VEA.US",
    "ticker_yfinance": null,
    "source": "stooq",
    "asset_type": "benchmark",
    "country": null,
    "sector": null,
    "hierarchy_level": 1,
    "benchmark_id": null,
    "currency": "USD",
    "liquidity_tier": 1
  }
]